ssha/__init__.py
ssha/__main__.py
ssha/aws.py
ssha/cli.py
ssha/config.py
ssha/ec2.py
ssha/errors.py
ssha/iam.py
ssha/menu.py
ssha/settings.py
ssha/ssh.py
ssha/ssm.py
ssha-2.0.2.data/scripts/ssha
ssha-2.0.2.dist-info/LICENSE
ssha-2.0.2.dist-info/METADATA
ssha-2.0.2.dist-info/WHEEL
ssha-2.0.2.dist-info/top_level.txt
ssha-2.0.2.dist-info/RECORD
