Metadata-Version: 2.1
Name: ssha
Version: 2.0.2
Summary: SSH into AWS EC2 instances
Home-page: https://github.com/claranet/ssha
Author: Raymond Butcher
Author-email: ray.butcher@claranet.uk
License: MIT License
Platform: UNKNOWN
Requires-Dist: boto-source-profile-mfa (>=0.0.8)
Requires-Dist: botocore (>=1.5.8)
Requires-Dist: boto3
Requires-Dist: cryptography
Requires-Dist: paramiko
Requires-Dist: pyhcl
